llm_jupyter/commands.py
llm_jupyter/magic.py
llm_jupyter-0.2.0.dist-info/LICENSE
llm_jupyter-0.2.0.dist-info/METADATA
llm_jupyter-0.2.0.dist-info/WHEEL
llm_jupyter-0.2.0.dist-info/entry_points.txt
llm_jupyter-0.2.0.dist-info/top_level.txt
llm_jupyter-0.2.0.dist-info/RECORD
