Metadata-Version: 2.1
Name: llm-jupyter
Version: 0.2.0
Summary: Run a IPython interpreter in the LLM virtual environment
Author: Simon Willison
Author-email: Lucas Rangel Cezimbra <lucas@cezimbra.tec.br>
License: Apache-2.0
Project-URL: Homepage, https://github.com/lucasrcezimbra/llm-jupyter
Project-URL: Changelog, https://github.com/lucasrcezimbra/llm-jupyter/releases
Project-URL: Issues, https://github.com/lucasrcezimbra/llm-jupyter/issues
Project-URL: CI, https://github.com/lucasrcezimbra/llm-jupyter/actions
Classifier: License :: OSI Approved :: Apache Software License
License-File: LICENSE
Requires-Dist: ipython
Requires-Dist: jupyter
Requires-Dist: llm
Provides-Extra: test
Requires-Dist: pytest ; extra == 'test'
Requires-Dist: pytest-mock ; extra == 'test'
